odoo/addons/mail_force_sender/__init__.py
odoo/addons/mail_force_sender/__manifest__.py
odoo/addons/mail_force_sender/hooks.py
odoo/addons/mail_force_sender/data/ir_config_parameter.xml
odoo/addons/mail_force_sender/models/__init__.py
odoo/addons/mail_force_sender/models/mail_thread.py
odoo12_addon_mail_force_sender-12.0.1.0.5.dist-info/METADATA
odoo12_addon_mail_force_sender-12.0.1.0.5.dist-info/WHEEL
odoo12_addon_mail_force_sender-12.0.1.0.5.dist-info/top_level.txt
odoo12_addon_mail_force_sender-12.0.1.0.5.dist-info/RECORD
